{
  "variants": {
    "starfish_amount=1,facing=up": [
      {
        "model": "seafarer:block/coral_starfish_0"
      },
      {
        "model": "seafarer:block/coral_starfish_0",
        "y": 90
      },
      {
        "model": "seafarer:block/coral_starfish_0",
        "y": 180
      },
      {
        "model": "seafarer:block/coral_starfish_0",
        "y": 270
      }
    ],
    "starfish_amount=2,facing=up": [
      {
        "model": "seafarer:block/coral_starfish_1"
      },
      {
        "model": "seafarer:block/coral_starfish_1",
        "y": 90
      },
      {
        "model": "seafarer:block/coral_starfish_1",
        "y": 180
      },
      {
        "model": "seafarer:block/coral_starfish_1",
        "y": 270
      }
    ],
    "starfish_amount=3,facing=up": [
      {
        "model": "seafarer:block/coral_starfish_2"
      },
      {
        "model": "seafarer:block/coral_starfish_2",
        "y": 90
      },
      {
        "model": "seafarer:block/coral_starfish_2",
        "y": 180
      },
      {
        "model": "seafarer:block/coral_starfish_2",
        "y": 270
      }
    ],
    "starfish_amount=1,facing=down": [
      {
        "model": "seafarer:block/coral_starfish_0",
        "x": 180
      },
      {
        "model": "seafarer:block/coral_starfish_0",
        "y": 90,
        "x": 180
      },
      {
        "model": "seafarer:block/coral_starfish_0",
        "y": 180,
        "x": 180
      },
      {
        "model": "seafarer:block/coral_starfish_0",
        "y": 270,
        "x": 180
      }
    ],
    "starfish_amount=2,facing=down": [
      {
        "model": "seafarer:block/coral_starfish_1",
        "x": 180
      },
      {
        "model": "seafarer:block/coral_starfish_1",
        "y": 90,
        "x": 180
      },
      {
        "model": "seafarer:block/coral_starfish_1",
        "y": 180,
        "x": 180
      },
      {
        "model": "seafarer:block/coral_starfish_1",
        "y": 270,
        "x": 180
      }
    ],
    "starfish_amount=3,facing=down": [
      {
        "model": "seafarer:block/coral_starfish_2",
        "x": 180
      },
      {
        "model": "seafarer:block/coral_starfish_2",
        "y": 90,
        "x": 180
      },
      {
        "model": "seafarer:block/coral_starfish_2",
        "y": 180,
        "x": 180
      },
      {
        "model": "seafarer:block/coral_starfish_2",
        "y": 270,
        "x": 180
      }
    ],
    "starfish_amount=1,facing=east": [
      {
        "model": "seafarer:block/coral_starfish_0",
        "x": 90,
        "y": 90
      },
      {
        "model": "seafarer:block/coral_starfish_0",
        "y": 270,
        "x": 270
      }
    ],
    "starfish_amount=2,facing=east": [
      {
        "model": "seafarer:block/coral_starfish_1",
        "x": 90,
        "y": 90
      },
      {
        "model": "seafarer:block/coral_starfish_1",
        "y": 270,
        "x": 270
      }
    ],
    "starfish_amount=3,facing=east": [
      {
        "model": "seafarer:block/coral_starfish_2",
        "x": 90,
        "y": 90
      },
      {
        "model": "seafarer:block/coral_starfish_2",
        "y": 270,
        "x": 270
      }
    ],

    "starfish_amount=1,facing=west": [
      {
        "model": "seafarer:block/coral_starfish_0",
        "x": 90,
        "y": 270
      },
      {
        "model": "seafarer:block/coral_starfish_0",
        "x": 270,
        "y": 90
      }
    ],
    "starfish_amount=2,facing=west": [
      {
        "model": "seafarer:block/coral_starfish_1",
        "x": 90,
        "y": 270
      },
      {
        "model": "seafarer:block/coral_starfish_1",
        "x": 270,
        "y": 90
      }
    ],
    "starfish_amount=3,facing=west": [
      {
        "model": "seafarer:block/coral_starfish_2",
        "x": 90,
        "y": 270
      },
      {
        "model": "seafarer:block/coral_starfish_2",
        "x": 270,
        "y": 90
      }
    ],
    "starfish_amount=1,facing=north": [
      {
        "model": "seafarer:block/coral_starfish_0",
        "x": 90
      },
      {
        "model": "seafarer:block/coral_starfish_0",
        "x": 270,
        "y": 180
      }
    ],
    "starfish_amount=2,facing=north": [
      {
        "model": "seafarer:block/coral_starfish_1",
        "x": 90
      },
      {
        "model": "seafarer:block/coral_starfish_1",
        "x": 270,
        "y": 180
      }
    ],
    "starfish_amount=3,facing=north": [
      {
        "model": "seafarer:block/coral_starfish_2",
        "x": 90
      },
      {
        "model": "seafarer:block/coral_starfish_2",
        "x": 270,
        "y": 180
      }
    ],
    "starfish_amount=1,facing=south": [
      {
        "model": "seafarer:block/coral_starfish_0",
        "x": 90,
        "y": 180
      },
      {
        "model": "seafarer:block/coral_starfish_0",
        "x": 270
      }
    ],
    "starfish_amount=2,facing=south": [
      {
        "model": "seafarer:block/coral_starfish_1",
        "x": 90,
        "y": 180
      },
      {
        "model": "seafarer:block/coral_starfish_1",
        "x": 270
      }
    ],
    "starfish_amount=3,facing=south": [
      {
        "model": "seafarer:block/coral_starfish_2",
        "x": 90,
        "y": 180
      },
      {
        "model": "seafarer:block/coral_starfish_2",
        "x": 270
      }
    ]
  }
}